pyazo_cli/__init__.py
pyazo_cli-0.4.1.dist-info/licenses/LICENSE
pyazo_cli-0.4.1.dist-info/METADATA
pyazo_cli-0.4.1.dist-info/WHEEL
pyazo_cli-0.4.1.dist-info/entry_points.txt
pyazo_cli-0.4.1.dist-info/top_level.txt
pyazo_cli-0.4.1.dist-info/RECORD
