Metadata-Version: 2.4
Name: pyazo_cli
Version: 0.4.1
Author-email: Jelena Dokic <jrubics@hacke.rs>, TheEdgeOfRage <git@theedgeofrage.com>
License-Expression: BSD-3-Clause
Classifier: Development Status :: 5 - Production/Stable
Classifier: Environment :: Console
Classifier: Operating System :: OS Independent
Classifier: Programming Language :: Python :: 3.9
Requires-Python: >=3.9
License-File: LICENSE
Requires-Dist: click>=8.1.8
Requires-Dist: pyclip>=0.7.0
Requires-Dist: requests>=2.32.4
Dynamic: license-file
